MANIFEST.in
setup.cfg
setup.py
django_spages.egg-info/PKG-INFO
django_spages.egg-info/SOURCES.txt
django_spages.egg-info/dependency_links.txt
django_spages.egg-info/not-zip-safe
django_spages.egg-info/requires.txt
django_spages.egg-info/top_level.txt
spages/__init__.py
spages/admin.py
spages/apps.py
spages/conf.py
spages/forms.py
spages/models.py
spages/serializers.py
spages/tests.py
spages/urls.py
spages/views.py
spages/management/__init__.py
spages/management/__init__.pyc
spages/management/conf.py
spages/management/conf.pyc
spages/management/commands/__init__.py
spages/management/commands/build_routes.py
spages/migrations/0001_initial.py
spages/migrations/__init__.py
spages/migrations/__init__.pyc
spages/static/jsoneditor/dist/jsoneditor-minimalist.js
spages/static/jsoneditor/dist/jsoneditor-minimalist.map
spages/static/jsoneditor/dist/jsoneditor-minimalist.min.js
spages/static/jsoneditor/dist/jsoneditor.css
spages/static/jsoneditor/dist/jsoneditor.js
spages/static/jsoneditor/dist/jsoneditor.js.map
spages/static/jsoneditor/dist/jsoneditor.map
spages/static/jsoneditor/dist/jsoneditor.min.css
spages/static/jsoneditor/dist/jsoneditor.min.js
spages/static/jsoneditor/dist/which files do I need.md
spages/static/jsoneditor/dist/img/jsoneditor-icons.svg
spages/templates/admin/spages/spage/change_form.html
spages/templates/admin/spages/spage/change_list.html
spages/templates/codemirror2/codemirror_script_spages.html
spages/templates/spages/client.js
spages/templates/spages/extra_async_handlers.js
spages/templates/spages/extra_handlers.js
spages/templates/spages/extra_routes.js
spages/templates/spages/index.html
spages/templates/spages/sitemap.html
spages/templates/spages/auto/routes.js
spages/templates/spages/spagelib/index.html
spages/templates/spages/spagelib/page.js
spages/templates/spages/spagelib/promise.min.js
spages/templatetags/__init__.py
spages/templatetags/__init__.pyc
spages/templatetags/spages_tags.py
spages/templatetags/spages_tags.pyc