Metadata-Version: 1.1
Name: django-spages
Version: 0.1.9
Summary: Lightweight single page app for Django
Home-page: https://github.com/synw/django-spages
Author: synw
Author-email: synwe@yahoo.com
License: UNKNOWN
Download-URL: https://github.com/synw/django-spages/releases/tag/0.1.9
Keywords: django,spa,page.js
Platform: UNKNOWN
Classifier: Development Status :: 3 - Alpha
Classifier: Framework :: Django :: 1.9
Classifier: Intended Audience :: Developers
Classifier: License :: OSI Approved :: MIT License
Classifier: Programming Language :: Python :: 2.7
